nqontrol/.gitignore
nqontrol/__init__.py
nqontrol/general/__init__.py
nqontrol/general/errors.py
nqontrol/general/helpers.py
nqontrol/general/mockAdwin.py
nqontrol/general/settings.py
nqontrol/general/settings_local.sample.py
nqontrol/gui/__init__.py
nqontrol/gui/assets/.gitignore
nqontrol/gui/assets/__init__.py
nqontrol/gui/assets/bootstrap.min.css
nqontrol/gui/assets/stylesheet.scss
nqontrol/gui/dependencies.py
nqontrol/gui/guniconfig.py
nqontrol/gui/gunirun.py
nqontrol/gui/run.py
nqontrol/gui/widgets/__init__.py
nqontrol/gui/widgets/_callbacks.py
nqontrol/gui/widgets/monitor_section/__init__.py
nqontrol/gui/widgets/monitor_section/_callbacks.py
nqontrol/gui/widgets/monitor_section/adwinMonitorsWidget.py
nqontrol/gui/widgets/monitor_section/digitalOsciWidget.py
nqontrol/gui/widgets/nqWidget.py
nqontrol/gui/widgets/second_order_section/__init__.py
nqontrol/gui/widgets/second_order_section/_callbacks.py
nqontrol/gui/widgets/second_order_section/filterWidget.py
nqontrol/gui/widgets/second_order_section/sosHeaderWidget.py
nqontrol/gui/widgets/second_order_section/sosWidget.py
nqontrol/gui/widgets/servo_section/__init__.py
nqontrol/gui/widgets/servo_section/_callbacks.py
nqontrol/gui/widgets/servo_section/autolockWidget.py
nqontrol/gui/widgets/servo_section/servoSwitchesWidget.py
nqontrol/gui/widgets/servo_section/servoWidget.py
nqontrol/gui/widgets/ui.py
nqontrol/servo/__init__.py
nqontrol/servo/_autolock.py
nqontrol/servo/_feedbackController.py
nqontrol/servo/_general.py
nqontrol/servo/_plotting.py
nqontrol/servo/_saveload.py
nqontrol/servo/_state.py
nqontrol/servo/_temp_feedback.py
nqontrol/servodevice/__init__.py
nqontrol/servodevice/_general.py
nqontrol/servodevice/_loadsave.py
nqontrol/servodevice/_monitors.py
nqontrol/servodevice/_servo_handling.py
nqontrol/servodevice/nqontrol.TC1
nqontrol-1.2.1.dist-info/entry_points.txt
nqontrol-1.2.1.dist-info/LICENSE
nqontrol-1.2.1.dist-info/WHEEL
nqontrol-1.2.1.dist-info/METADATA
nqontrol-1.2.1.dist-info/RECORD
