Metadata-Version: 2.1
Name: nqontrol
Version: 1.2.1
Summary: Python program for digital control-loops.
Home-page: https://gitlab.com/las-nq/nqontrol
Author: Christian Darsow-Fromm
Author-email: cdarsowf@physnet.uni-hamburg.de
Requires-Python: >=3.6.1,<4.0.0
Classifier: Programming Language :: Python :: 3
Classifier: Programming Language :: Python :: 3.7
Classifier: Programming Language :: Python :: 3.8
Classifier: Programming Language :: Python :: 3.9
Requires-Dist: ADwin (>=0.16.2,<0.17.0)
Requires-Dist: Flask (>=1.1.2,<2.0.0)
Requires-Dist: dash (>=1.11.0,<2.0.0)
Requires-Dist: dash_daq (>=0.5.0,<0.6.0)
Requires-Dist: fastnumbers (>=3.0.0,<4.0.0)
Requires-Dist: gunicorn (>=20.0.4,<21.0.0)
Requires-Dist: importlib-metadata (>=1.6,<2.0); python_version <= "3.7"
Requires-Dist: jsonpickle (>=1.4,<2.0)
Requires-Dist: matplotlib (>=3.2.1,<4.0.0)
Requires-Dist: numpy (>=1.14,<2.0)
Requires-Dist: openqlab (>=0.3.0,<0.4.0)
Requires-Dist: pandas (>=1.0,<2.0)
Requires-Dist: plotly (>=4.3,<5.0)
Requires-Dist: scipy (>=1.0,<2.0)
Requires-Dist: websocket_client (>=0.57.0,<0.58.0)
Project-URL: Documentation, https://las-nq-serv.physnet.uni-hamburg.de/python/nqontrol/
Project-URL: Repository, https://gitlab.com/las-nq/nqontrol
